lasvsim_openapi/__init__.py
lasvsim_openapi/client.py
lasvsim_openapi/client_fast.py
lasvsim_openapi/http_client.py
lasvsim_openapi/opensim.py
lasvsim_openapi/process_task.py
lasvsim_openapi/process_task_fast.py
lasvsim_openapi/process_task_model.py
lasvsim_openapi/qxmap.py
lasvsim_openapi/qxmap_model.py
lasvsim_openapi/request_model.py
lasvsim_openapi/resources.py
lasvsim_openapi/resources_fast.py
lasvsim_openapi/response_model.py
lasvsim_openapi/sim_record.py
lasvsim_openapi/sim_record_fast.py
lasvsim_openapi/sim_record_model.py
lasvsim_openapi/simulator.py
lasvsim_openapi/simulator_fast.py
lasvsim_openapi/simulator_model.py
lasvsim_openapi/train_task.py
lasvsim_openapi/train_task_fast.py
lasvsim_openapi/train_task_model.py
lasvsim_openapi-0.1.16.dist-info/METADATA
lasvsim_openapi-0.1.16.dist-info/WHEEL
lasvsim_openapi-0.1.16.dist-info/cosim_task.py
lasvsim_openapi-0.1.16.dist-info/top_level.txt
lasvsim_openapi-0.1.16.dist-info/RECORD
